README.md
setup.py
pulumi_sakuracloud/__init__.py
pulumi_sakuracloud/_inputs.py
pulumi_sakuracloud/_utilities.py
pulumi_sakuracloud/archive.py
pulumi_sakuracloud/archive_share.py
pulumi_sakuracloud/auto_backup.py
pulumi_sakuracloud/bridge.py
pulumi_sakuracloud/cdrom.py
pulumi_sakuracloud/certificate_authority.py
pulumi_sakuracloud/container_registry.py
pulumi_sakuracloud/database.py
pulumi_sakuracloud/database_read_replica.py
pulumi_sakuracloud/disk.py
pulumi_sakuracloud/dns.py
pulumi_sakuracloud/dns_record.py
pulumi_sakuracloud/enhanced_db.py
pulumi_sakuracloud/esme.py
pulumi_sakuracloud/get_archive.py
pulumi_sakuracloud/get_bridge.py
pulumi_sakuracloud/get_cdrom.py
pulumi_sakuracloud/get_certificate_authority.py
pulumi_sakuracloud/get_container_registry.py
pulumi_sakuracloud/get_database.py
pulumi_sakuracloud/get_disk.py
pulumi_sakuracloud/get_dns.py
pulumi_sakuracloud/get_enhanced_db.py
pulumi_sakuracloud/get_esme.py
pulumi_sakuracloud/get_gslb.py
pulumi_sakuracloud/get_icon.py
pulumi_sakuracloud/get_internet.py
pulumi_sakuracloud/get_load_balancer.py
pulumi_sakuracloud/get_local_router.py
pulumi_sakuracloud/get_nfs.py
pulumi_sakuracloud/get_note.py
pulumi_sakuracloud/get_packet_filter.py
pulumi_sakuracloud/get_private_host.py
pulumi_sakuracloud/get_proxy_lb.py
pulumi_sakuracloud/get_server.py
pulumi_sakuracloud/get_server_vnc_info.py
pulumi_sakuracloud/get_simple_monitor.py
pulumi_sakuracloud/get_ssh_key.py
pulumi_sakuracloud/get_subnet.py
pulumi_sakuracloud/get_switch.py
pulumi_sakuracloud/get_vpc_router.py
pulumi_sakuracloud/get_web_accel.py
pulumi_sakuracloud/get_zone.py
pulumi_sakuracloud/gslb.py
pulumi_sakuracloud/i_pv4_ptr.py
pulumi_sakuracloud/icon.py
pulumi_sakuracloud/internet.py
pulumi_sakuracloud/load_balancer.py
pulumi_sakuracloud/local_router.py
pulumi_sakuracloud/mobile_gateway.py
pulumi_sakuracloud/nfs.py
pulumi_sakuracloud/note.py
pulumi_sakuracloud/outputs.py
pulumi_sakuracloud/packet_filter.py
pulumi_sakuracloud/packet_filter_rule.py
pulumi_sakuracloud.egg-info/PKG-INFO
pulumi_sakuracloud.egg-info/SOURCES.txt
pulumi_sakuracloud.egg-info/dependency_links.txt
pulumi_sakuracloud.egg-info/not-zip-safe
pulumi_sakuracloud.egg-info/requires.txt
pulumi_sakuracloud.egg-info/top_level.txt
