Metadata-Version: 2.1
Name: pulumi-sakuracloud
Version: 0.6.0
Summary: A Pulumi package for creating and managing SakuraCloud resources.
Home-page: https://github.com/sacloud/pulumi-sakuracloud
License: Apache-2.0
Project-URL: Repository, https://github.com/sacloud/pulumi-sakuracloud
Keywords: pulumi sakuracloud
Platform: UNKNOWN
